{
    "categorias": [
    {
        "id": 1,
        "titulo": "Semear",
        "descricao": "Videos da semear",
        "cor": "#FFF000"
    },
    {
        "id": 2,
        "titulo": "Pregações",
        "descricao": "Algumas pregações",
        "cor": "#00C86F"
    },
    {
        "id": 3,
        "titulo": "Mensagens rapidas",
        "descricao": "Pra ouvir no tempo apertado",
        "cor": "#6BD1FF"
    },
    {
        "id": 4,
        "titulo": "Testemunhos",
        "descricao": "Pra somar",
        "cor": "##ffd27f"
    },
    {
        "id": 5,
        "titulo": "Estudos",
        "descricao": "Estudos a fundo no cristianismo",
        "cor": "#40e0d0"
    }
    ],  
    "videos": [
        {
            "id": 1,
            "categoriaId": 1,
            "titulo": "Vida com Deus | Stephanie Milagre",
            "url": "https://www.youtube.com/watch?v=bVyeGPWjMDg&t"
        },
        {
            "id": 2,
            "categoriaId": 2,
            "titulo": "A palavra que realmente importa | Rodolfo Abrantes",
            "url": "https://www.youtube.com/watch?v=T5AUHWH1R4s"
        },
        {
            "id": 3,
            "categoriaId": 3,
            "titulo": "ESTOU CANSADO | ANDRÉ FERNANDES",
            "url": "https://www.youtube.com/watch?v=2GDVt0XDvWU"
        },
        {
            "id": 4,
            "categoriaId": 4,
            "titulo": "Nova Coluna Como de Um Bebê | Luciano Subirá",
            "url": "https://www.youtube.com/watch?v=zMFgxwZCf_Y"
        },
        {
            "id": 5,
            "categoriaId": 5,
            "titulo": "A História do Cristianismo Como Você Nunca Viu - Episódio 01 | Escola do Discipulo",
            "url": "https://www.youtube.com/watch?v=KmpucxGB1jA"
        }
      ]
    }
    